{"date": 1609714800, "frontpage": {"Wähleranteile": "Union zwischen 37 % und 35 %, SPD zwischen 16 % und 14 % Grüne bei 21 % bzw. 18 %, AfD bei 10 % bzw. 9 %", "Wirtschaft": "Gut die Hälfte der Bevölkerung erwartet Verschlechterung der ökonomischen Lage", "Weltpolitische Lage": "57 % machen sich keine Sorgen um den Weltfrieden Krankheiten werden als größte Bedrohung wahrgenommen Weniger Bürger finden, dass Deutschland mehr Verantwortung in der Weltpolitik übernehmen sollte", "Wichtigste Themen": "Coronavirus"}, "tables": {"Wähleranteile": [{"key": "CDU/CSU", "forsa1 für RTL/n-tv": "36", "GMS2": "37", "infratest dimap3 für ARD": "35"}, {"key": "SPD", "forsa1 für RTL/n-tv": "15", "GMS2": "16", "infratest dimap3 für ARD": "14"}, {"key": "FDP", "forsa1 für RTL/n-tv": "6", "GMS2": "6", "infratest dimap3 für ARD": "7"}, {"key": "DIE LINKE", "forsa1 für RTL/n-tv": "9", "GMS2": "8", "infratest dimap3 für ARD": "7"}, {"key": "B'90/Grüne", "forsa1 für RTL/n-tv": "18", "GMS2": "18", "infratest dimap3 für ARD": "21"}, {"key": "AfD", "forsa1 für RTL/n-tv": "9", "GMS2": "9", "infratest dimap3 für ARD": "10"}, {"key": "Sonstige", "forsa1 für RTL/n-tv": "7", "GMS2": "6", "infratest dimap3 für ARD": "6"}, {"key": "Erhebungszeitraum", "forsa1 für RTL/n-tv": "21.-23.12.", "GMS2": "29.12.-04.01.", "infratest dimap3 für ARD": "04.-06.01."}], "Kanzlerpräferenz": [{"key": "Markus Söder", "forsa für RTL/n-tv": "35"}, {"key": "Olaf Scholz", "forsa für RTL/n-tv": "15"}, {"key": "Robert Habeck", "forsa für RTL/n-tv": "19"}, {"key": "keinen davon", "forsa für RTL/n-tv": "31"}, {"key": "Erhebungszeitraum", "forsa für RTL/n-tv": "21.-23.12."}], "Problemlösungskompetenz": [{"key": "CDU/CSU", "forsa für RTL/n-tv": "40"}, {"key": "SPD", "forsa für RTL/n-tv": "5"}, {"key": "Grüne", "forsa für RTL/n-tv": "5"}, {"key": "sonstige Parteien", "forsa für RTL/n-tv": "5"}, {"key": "keine Partei", "forsa für RTL/n-tv": "45"}, {"key": "Erhebungszeitraum", "forsa für RTL/n-tv": "21.-23.12."}], "Langfristige Erwartungen für die Wirtschaft": [{"key": "besser", "forsa für RTL/n-tv": "22"}, {"key": "schlechter", "forsa für RTL/n-tv": "53"}, {"key": "unverändert", "forsa für RTL/n-tv": "22"}, {"key": "Erhebungszeitraum", "forsa für RTL/n-tv": "21.-23.12."}], "Machen Sie sich Sorgen um den Weltfrieden?": [{"key": "sehr große", "forsa für BPA": "9"}, {"key": "große", "forsa für BPA": "34"}, {"key": "wenig", "forsa für BPA": "45"}, {"key": "keine", "forsa für BPA": "12"}, {"key": "Erhebungszeitraum", "forsa für BPA": "21.-23.12."}], "Weltweite Krisen(regionen) als Gefahrenquelle für Deutschland": [{"key": "Krankheiten: Coronavirus", "forsa für BPA": "28"}, {"key": "Umwelt-/Klimakrise", "forsa für BPA": "13"}, {"key": "(Welt-)Wirtschaftskrise", "forsa für BPA": "9"}, {"key": "Asylbewerber, Flüchtlinge", "forsa für BPA": "8"}, {"key": "Naher Osten, arabische Länder", "forsa für BPA": "7"}, {"key": "USA", "forsa für BPA": "6"}, {"key": "China", "forsa für BPA": "6"}, {"key": "Krieg, Terrorismus allgemein", "forsa für BPA": "5"}, {"key": "Erhebungszeitraum", "forsa für BPA": "21.-23.12."}], "Rolle Deutschlands in der Weltpolitik": [{"key": "sollte mehr Verant- wortung übernehmen", "forsa für BPA": "40"}, {"key": "sollte weniger Verant- wortung übernehmen", "forsa für BPA": "9"}, {"key": "Deutschland tut bereits genug", "forsa für BPA": "48"}, {"key": "Erhebungszeitraum", "forsa für BPA": "21.-23.12."}], "Rolle Deutschlands in der EU": [{"key": "nimmt zu viel Rücksicht auf andere EU-Mitgliedstaaten", "forsa für BPA": "39"}, {"key": "nimmt zu wenig Rücksicht auf andere EU-Mitgliedstaaten", "forsa für BPA": "12"}, {"key": "verhält sich alles in allem genau richtig", "forsa für BPA": "45"}, {"key": "Erhebungszeitraum", "forsa für BPA": "21.-23.12."}], "Wichtigste Themen": [{"key": "Coronavirus", "forsa für BPA": "65"}, {"key": "Ausgangs- und Kontaktsperre", "forsa für BPA": "19"}, {"key": "USA: Präsident Trump, Wahl", "forsa für BPA": "15"}, {"key": "Corona-Impfung", "forsa für BPA": "13"}, {"key": "Allgemeine Wirtschaftslage", "forsa für BPA": "6"}, {"key": "Schulbetrieb unter Corona-Bedingungen", "forsa für BPA": "6"}, {"key": "Erhebungszeitraum", "forsa für BPA": "04.-06.01."}]}, "errors": []}