{"date": 1463349600, "frontpage": {"Wähleranteile": "Union zwischen 34 % und 32 %, SPD zwischen 22 % und 19 %", "Wirtschaft": "Pessimistische Erwartungen überwiegen", "Weltpolitische Lage": "Sorge um den Weltfrieden Flüchtlingskrise und Lage in Syrien werden als größte Bedrohung wahr- genommen", "Flüchtlinge": "Erstmals überwiegt der Anteil derer, die sich keine Sorgen über die Flüchtlingsaufnahme in Deutschland machen Bürger sehen weiterhin eher keine Fortschritte bei Bewältigung der Krise", "Wichtigstes Thema": "Flüchtlingsströme/Europäische Einwanderungspolitik"}, "tables": {"Wähleranteile": [{"key": "CDU/CSU", "forsa für RTL/stern": "34", "Emnid1 für BamS": "32", "IfD Allensbach2 für FAZ": "33,5", "infratest dimap3 für ARD": "32"}, {"key": "SPD", "forsa für RTL/stern": "19", "Emnid1 für BamS": "22", "IfD Allensbach2 für FAZ": "21,0", "infratest dimap3 für ARD": "21"}, {"key": "FDP", "forsa für RTL/stern": "7", "Emnid1 für BamS": "6", "IfD Allensbach2 für FAZ": "8,0", "infratest dimap3 für ARD": "7"}, {"key": "DIE LINKE", "forsa für RTL/stern": "9", "Emnid1 für BamS": "9", "IfD Allensbach2 für FAZ": "9,0", "infratest dimap3 für ARD": "9"}, {"key": "B'90/Grüne", "forsa für RTL/stern": "14", "Emnid1 für BamS": "12", "IfD Allensbach2 für FAZ": "11,5", "infratest dimap3 für ARD": "12"}, {"key": "AfD", "forsa für RTL/stern": "11", "Emnid1 für BamS": "13", "IfD Allensbach2 für FAZ": "12,5", "infratest dimap3 für ARD": "15"}, {"key": "Sonstige", "forsa für RTL/stern": "6", "Emnid1 für BamS": "6", "IfD Allensbach2 für FAZ": "4,5", "infratest dimap3 für ARD": "4"}, {"key": "Erhebungszeitraum", "forsa für RTL/stern": "09.-13.05.", "Emnid1 für BamS": "13.-18.05.", "IfD Allensbach2 für FAZ": "28.04.-12.05.", "infratest dimap3 für ARD": "17.-18.05."}], "Kanzlerpräferenz": [{"key": "Merkel", "forsa für RTL/stern": "46"}, {"key": "Gabriel", "forsa für RTL/stern": "15"}, {"key": "Erhebungszeitraum", "forsa für RTL/stern": "09.-13.05."}], "Problemlösungskompetenz": [{"key": "CDU/CSU", "forsa für RTL/stern": "25"}, {"key": "SPD", "forsa für RTL/stern": "7"}, {"key": "sonstige Parteien", "forsa für RTL/stern": "12"}, {"key": "keine Partei", "forsa für RTL/stern": "56"}, {"key": "Erhebungszeitraum", "forsa für RTL/stern": "09.-13.05."}], "Langfristige Erwartungen für die Wirtschaft": [{"key": "besser", "forsa für RTL/stern": "18"}, {"key": "schlechter", "forsa für RTL/stern": "44"}, {"key": "unverändert", "forsa für RTL/stern": "36"}, {"key": "Erhebungszeitraum", "forsa für RTL/stern": "09.-13.05."}], "Machen Sie sich Sorgen um den Weltfrieden?": [{"key": "sehr große", "forsa für BPA": "12"}, {"key": "große", "forsa für BPA": "48"}, {"key": "wenig", "forsa für BPA": "31"}, {"key": "keine", "forsa für BPA": "8"}, {"key": "Erhebungszeitraum", "forsa für BPA": "09.-13.05."}], "Von welcher weltweiten Krise droht Deutschland aktuell die größte Gefahr?": [{"key": "Asylbewerber, Flüchtlinge", "forsa für BPA": "15"}, {"key": "Syrien", "forsa für BPA": "15"}, {"key": "Islamischer Staat", "forsa für BPA": "13"}, {"key": "Krieg/Terrorismus allgemein", "forsa für BPA": "10"}, {"key": "Naher Osten, arabische Länder", "forsa für BPA": "8"}, {"key": "Russland", "forsa für BPA": "6"}, {"key": "Religion, religiöse Krisen/Kriege allgemein", "forsa für BPA": "6"}, {"key": "Ukraine", "forsa für BPA": "5"}, {"key": "USA", "forsa für BPA": "5"}, {"key": "Türkei", "forsa für BPA": "5"}, {"key": "Erhebungszeitraum", "forsa für BPA": "09.-13.05."}], "Rolle Deutschlands in der Weltpolitik": [{"key": "sollte mehr Verant- wortung übernehmen", "forsa für BPA": "29"}, {"key": "sollte weniger Verant- wortung übernehmen", "forsa für BPA": "10"}, {"key": "Deutschland tut bereits genug", "forsa für BPA": "58"}, {"key": "Erhebungszeitraum", "forsa für BPA": "09.-13.05."}], "Rolle Deutschlands in der EU": [{"key": "nimmt zu viel Rücksicht auf andere EU-Mitgliedstaaten", "forsa für BPA": "42"}, {"key": "nimmt zu wenig Rücksicht auf andere EU-Mitgliedstaaten", "forsa für BPA": "14"}, {"key": "verhält sich alles in allem genau richtig", "forsa für BPA": "39"}, {"key": "Erhebungszeitraum", "forsa für BPA": "09.-13.05."}], "Machen Sie sich Sorgen, dass so viele Flüchtlinge nach Deutschland kommen?": [{"key": "mache mir Sorgen", "Emnid für BPA": "46"}, {"key": "mache mir keine Sorgen", "Emnid für BPA": "51"}, {"key": "Erhebungszeitraum", "Emnid für BPA": "11.-17.05."}], "Hat die Aufnahme von Flüchtlingen kurzfristig bzw. langfristig für Deutschland …?": [{"key": "eher Vorteile", "kurzfristig": "7", "langfristig": "21"}, {"key": "eher Nachteile", "kurzfristig": "49", "langfristig": "31"}, {"key": "Vor- und Nachteile gleichen sich in etwa aus", "kurzfristig": "38", "langfristig": "40"}, {"key": "Erhebungszeitraum", "kurzfristig": "11.-17.05.", "langfristig": ""}], "Kommt die Bundesregierung bei der Bewältigung der Flüchtlingskrise …?": [{"key": "eher voran", "Emnid für BPA": "27"}, {"key": "eher nicht voran", "Emnid für BPA": "65"}, {"key": "Erhebungszeitraum", "Emnid für BPA": "11.-17.05."}], "Wichtigste Themen": [{"key": "Flüchtlingsströme/Europäische Einwanderungspolitik", "infratest dimap für BPA": "43"}, {"key": "Ausländer in Deutschland, Zuwanderungs-, Asylpolitik", "infratest dimap für BPA": "8"}, {"key": "Rentenpolitik/Altersvorsorge", "infratest dimap für BPA": "7"}, {"key": "Verhandlungen mit der Türkei, Verhalten der türkischen Regierung", "infratest dimap für BPA": "6"}, {"key": "Freihandelsabkommen zwischen EU und USA, TTIP", "infratest dimap für BPA": "6"}, {"key": "Erhebungszeitraum", "infratest dimap für BPA": "17.-18.05."}]}, "errors": []}